AUTHORS
LICENSE
MANIFEST.in
README.md
pyproject.toml
setup.py
django_spam/__init__.py
django_spam/apps.py
django_spam/enums.py
django_spam/urls.py
django_spam/utils.py
django_spam.egg-info/PKG-INFO
django_spam.egg-info/SOURCES.txt
django_spam.egg-info/dependency_links.txt
django_spam.egg-info/not-zip-safe
django_spam.egg-info/requires.txt
django_spam.egg-info/top_level.txt
tests/__init__.py
tests/settings.py
tests/test_spam.py
tests/test_utils.py
tests/urls.py