Metadata-Version: 2.1
Name: django-spam
Version: 2.0.0
Summary: Redirecting bots to utilize their time better...
Home-page: http://github.com/Tivix/django-spam
Author: Nick Kelly
Author-email: nick.kelly@tivix.com
License: UNKNOWN
Keywords: django spam
Platform: UNKNOWN
Classifier: Framework :: Django
Classifier: Framework :: Django :: 2.0
Classifier: Framework :: Django :: 2.1
Classifier: Framework :: Django :: 2.2
Classifier: Framework :: Django :: 3.0
Classifier: Framework :: Django :: 3.1
Classifier: Intended Audience :: Developers
Classifier: Intended Audience :: System Administrators
Classifier: Operating System :: OS Independent
Classifier: Topic :: Software Development
